.DS_Store
._.DS_Store
cloudlog/__init__.py
cloudlog/cloudlog.py
cloudlog-0.1.1.dist-info/DESCRIPTION.rst
cloudlog-0.1.1.dist-info/METADATA
cloudlog-0.1.1.dist-info/RECORD
cloudlog-0.1.1.dist-info/WHEEL
cloudlog-0.1.1.dist-info/metadata.json
cloudlog-0.1.1.dist-info/top_level.txt
